Metadata-Version: 2.1
Name: nextcord-ext-alternatives
Version: 2021.1
Summary: A nextcord extension with additional and alternative features, Forked from discord-ext-alternatives
Home-page: https://github.com/nextcord/alternatives
Author: nextcord-ext
License: Apache Software License
Project-URL: Issue Tracker, https://github.com/nextcord-ext/alternatives/issues
Project-URL: Source, https://github.com/nextcord-ext/alternatives
Platform: UNKNOWN
Classifier: Development Status :: 5 - Production/Stable
Classifier: Intended Audience :: Developers
Classifier: License :: OSI Approved :: Apache Software License
Classifier: Natural Language :: English
Classifier: Operating System :: OS Independent
Classifier: Programming Language :: Python :: 3
Classifier: Programming Language :: Python :: 3 :: Only
Classifier: Programming Language :: Python :: 3.5
Classifier: Programming Language :: Python :: 3.6
Classifier: Programming Language :: Python :: 3.7
Classifier: Programming Language :: Python :: 3.8
Classifier: Programming Language :: Python :: 3.9
Classifier: Programming Language :: Python :: Implementation :: CPython
Classifier: Topic :: Software Development
Classifier: Topic :: Software Development :: Libraries
Classifier: Topic :: Software Development :: Libraries :: Python Modules
License-File: LICENSE
Requires-Dist: nextcord (==2.0.0a)
